tableau_rest/Auth.py
tableau_rest/Datasources.py
tableau_rest/Favourites.py
tableau_rest/Jobs.py
tableau_rest/Permissions.py
tableau_rest/Projects.py
tableau_rest/Publish.py
tableau_rest/Revisions.py
tableau_rest/Server.py
tableau_rest/Sites.py
tableau_rest/Subscriptions.py
tableau_rest/Tools.py
tableau_rest/Users.py
tableau_rest/Workbooks.py
tableau_rest/__init__.py
tableau_rest_dronarc-0.0.5.dist-info/LICENSE
tableau_rest_dronarc-0.0.5.dist-info/METADATA
tableau_rest_dronarc-0.0.5.dist-info/WHEEL
tableau_rest_dronarc-0.0.5.dist-info/top_level.txt
tableau_rest_dronarc-0.0.5.dist-info/RECORD
