Metadata-Version: 2.1
Name: tableau-rest-dronarc
Version: 0.0.5
Summary: A object oreintated approach to Tableau REST interaction. Built to be as generic and modular as possible whilst automating Tableau Server Admin activities.
Home-page: https://github.com/Sam-Holmes
Author: Sam Holmes
Author-email: dronarc@gmail.com
License: UNKNOWN
Platform: UNKNOWN
Classifier: Programming Language :: Python :: 3
Classifier: License :: OSI Approved :: MIT License
Classifier: Operating System :: OS Independent
